ravyn/__init__.py
ravyn/__main__.py
ravyn/applications.py
ravyn/background.py
ravyn/context.py
ravyn/encoders.py
ravyn/exception_handlers.py
ravyn/exceptions.py
ravyn/injector.py
ravyn/logging.py
ravyn/param_functions.py
ravyn/params.py
ravyn/parsers.py
ravyn/py.typed
ravyn/requests.py
ravyn/staticfiles.py
ravyn/testclient.py
ravyn/types.py
ravyn/typing.py
ravyn/websockets.py
ravyn/conf/__init__.py
ravyn/conf/enums.py
ravyn/conf/global_settings.py
ravyn/conf/directives/__init__.py
ravyn/conf/directives/app_template/__init__.py-tpl
ravyn/conf/directives/app_template/tests.py-tpl
ravyn/conf/directives/app_template/directives/__init__.py-tpl
ravyn/conf/directives/app_template/directives/operations/__init__.py-tpl
ravyn/conf/directives/app_template/{{ api_version }}/__init__.py-tpl
ravyn/conf/directives/app_template/{{ api_version }}/controllers.py-tpl
ravyn/conf/directives/app_template/{{ api_version }}/schemas.py-tpl
ravyn/conf/directives/app_template/{{ api_version }}/urls.py-tpl
ravyn/conf/directives/app_template_context/__init__.py-tpl
ravyn/conf/directives/app_template_context/controllers.py-tpl
ravyn/conf/directives/app_template_context/dtos.py-tpl
ravyn/conf/directives/app_template_context/repository.py-tpl
ravyn/conf/directives/app_template_context/service.py-tpl
ravyn/conf/directives/app_template_context/tests.py-tpl
ravyn/conf/directives/app_template_context/urls.py-tpl
ravyn/conf/directives/app_template_context/directives/__init__.py-tpl
ravyn/conf/directives/app_template_context/directives/operations/__init__.py-tpl
ravyn/conf/directives/deployment_template/docker/Dockerfile.e-tpl
ravyn/conf/directives/deployment_template/gunicorn/gunicorn_conf.py.e-tpl
ravyn/conf/directives/deployment_template/nginx/nginx.conf.e-tpl
ravyn/conf/directives/deployment_template/nginx/nginx.json-logging.conf.e-tpl
ravyn/conf/directives/deployment_template/supervisor/supervisord.conf.e-tpl
ravyn/conf/directives/project_template/.gitignore.e-tpl
ravyn-0.3.5.dist-info/METADATA
ravyn-0.3.5.dist-info/WHEEL
ravyn-0.3.5.dist-info/entry_points.txt
ravyn-0.3.5.dist-info/licenses/LICENSE
ravyn-0.3.5.dist-info/RECORD
