Metadata-Version: 2.4
Name: ravyn
Version: 0.3.5
Summary: Ravyn combines performance, type safety, and elegance. A next-generation async Python framework for APIs, microservices, and web applications.
Project-URL: Homepage, https://github.com/dymmond/ravyn
Project-URL: Documentation, https://ravyn.dymmond.com/
Project-URL: Changelog, https://ravyn.dymmond.com/release-notes/
Project-URL: Funding, https://github.com/sponsors/tarsil
Project-URL: Source, https://github.com/dymmond/ravyn
Author-email: Tiago Silva <tiago.silva@dymmond.com>
Maintainer: devkral, kokoserver
Maintainer-email: Tiago Silva <tiago.silva@dymmond.com>
License-Expression: BSD-3-Clause
License-File: LICENSE
Keywords: ai,aiohttp,anyio,aop,api,api-key,api-server,asgi,async,async-framework,asyncio,authentication,auto-documentation,autodoc,backend,background-tasks,caching,cloud-native,concurrency,controllers,cors,csrf,data-validation,dependency-injection,developer-friendly,django,dymmond,esmerald,event-driven,exception-handling,fastapi,flask,graphql,graphql-support,high-performance,http,hypercorn,interceptors,json,jwt,lilya,machine-learning,microservices,middlewares,ml,modern-python,non-blocking,oauth2
Classifier: Development Status :: 5 - Production/Stable
Classifier: Environment :: Web Environment
Classifier: Framework :: AnyIO
Classifier: Framework :: AsyncIO
Classifier: Intended Audience :: Developers
Classifier: Intended Audience :: Information Technology
Classifier: Intended Audience :: System Administrators
Classifier: Operating System :: OS Independent
Classifier: Programming Language :: Python
Classifier: Programming Language :: Python :: 3
Classifier: Programming Language :: Python :: 3 :: Only
Classifier: Programming Language :: Python :: 3.10
Classifier: Programming Language :: Python :: 3.11
Classifier: Programming Language :: Python :: 3.12
Classifier: Programming Language :: Python :: 3.13
Classifier: Programming Language :: Python :: 3.14
Classifier: Topic :: Internet
Classifier: Topic :: Internet :: WWW/HTTP
Classifier: Topic :: Internet :: WWW/HTTP :: HTTP Servers
Classifier: Topic :: Software Development
Classifier: Topic :: Software Development :: Libraries
Classifier: Topic :: Software Development :: Libraries :: Application Frameworks
Classifier: Topic :: Software Development :: Libraries :: Python Modules
Classifier: Typing :: Typed
Requires-Python: >=3.10
Requires-Dist: lilya[standard]>=0.23.1
Requires-Dist: monkay>=0.5.0
Requires-Dist: msgspec<0.21.0,>=0.20.0
Requires-Dist: orjson<4.0.0,>=3.8.5
Requires-Dist: pydantic-settings>=2.9.0
Provides-Extra: all
Requires-Dist: a2wsgi; extra == 'all'
Requires-Dist: asyncz>=0.11.0; extra == 'all'
Requires-Dist: bcrypt>=4.3.0; extra == 'all'
Requires-Dist: email-validator<3.0.0,>=2.2.0; extra == 'all'
Requires-Dist: httpx<0.30.0,>=0.25.0; extra == 'all'
Requires-Dist: httpx>=0.25.0; extra == 'all'
Requires-Dist: ipython; extra == 'all'
Requires-Dist: itsdangerous<3.0.0,>=2.1.2; extra == 'all'
Requires-Dist: jinja2<4.0.0,>=3.1.2; extra == 'all'
Requires-Dist: ptpython; extra == 'all'
Requires-Dist: pyjwt<3,>=2.10.1; extra == 'all'
Requires-Dist: uvicorn[standard]>=0.37.0; extra == 'all'
Provides-Extra: dev
Requires-Dist: uvicorn[standard]>=0.37.0; extra == 'dev'
Provides-Extra: docs
Requires-Dist: a2wsgi>=1.9.0; extra == 'docs'
Requires-Dist: griffe-typingdoc<1.0,>=0.2.2; extra == 'docs'
Requires-Dist: httpx>=0.25.0; extra == 'docs'
Requires-Dist: lilya[standard]>=0.23.1; extra == 'docs'
Requires-Dist: mdx-include>=1.4.2; extra == 'docs'
Requires-Dist: mkdocs-macros-plugin>=0.4.0; extra == 'docs'
Requires-Dist: mkdocs-material>=9.4.4; extra == 'docs'
Requires-Dist: mkdocs-meta-descriptions-plugin>=2.3.0; extra == 'docs'
Requires-Dist: mkdocs<2.0.0,>=1.1.2; extra == 'docs'
Requires-Dist: mkdocstrings[python]>=0.23.0; extra == 'docs'
Requires-Dist: pyyaml<7.0.0,>=6.0; extra == 'docs'
Requires-Dist: typing-extensions>=3.10.0; extra == 'docs'
Provides-Extra: jwt
Requires-Dist: bcrypt>=4.3.0; extra == 'jwt'
Requires-Dist: pyjwt<3,>=2.10.1; extra == 'jwt'
Provides-Extra: schedulers
Requires-Dist: asyncz>=0.11.0; extra == 'schedulers'
Provides-Extra: standard
Requires-Dist: a2wsgi; extra == 'standard'
Requires-Dist: email-validator<3.0.0,>=2.2.0; extra == 'standard'
Requires-Dist: httpx<0.30.0,>=0.25.0; extra == 'standard'
Requires-Dist: itsdangerous<3.0.0,>=2.1.2; extra == 'standard'
Requires-Dist: jinja2<4.0.0,>=3.1.2; extra == 'standard'
Requires-Dist: uvicorn[standard]>=0.37.0; extra == 'standard'
Provides-Extra: test
Requires-Dist: httpx>=0.25.0; extra == 'test'
Provides-Extra: testing
Requires-Dist: anyio[trio]<5.0.0,>=3.6.2; extra == 'testing'
Requires-Dist: brotli<2.0.0,>=1.0.9; extra == 'testing'
Requires-Dist: databasez>=0.9.7; extra == 'testing'
Requires-Dist: edgy[postgres]>=0.31.3; extra == 'testing'
Requires-Dist: fakeredis>=2.27.0; extra == 'testing'
Requires-Dist: fastapi>=0.121.1; extra == 'testing'
Requires-Dist: flask<4.0.0,>=1.1.2; extra == 'testing'
Requires-Dist: freezegun<2.0.0,>=1.2.2; extra == 'testing'
Requires-Dist: grpcio-tools>=1.71.0; extra == 'testing'
Requires-Dist: ipdb; extra == 'testing'
Requires-Dist: litestar>=2.18.0; extra == 'testing'
Requires-Dist: loguru<0.8.0,>=0.7.0; extra == 'testing'
Requires-Dist: mongoz>=0.13.0; extra == 'testing'
Requires-Dist: mypy==1.19.1; extra == 'testing'
Requires-Dist: polyfactory<4.0.0,>=2.5.0; extra == 'testing'
Requires-Dist: pytest-asyncio>=0.26.0; extra == 'testing'
Requires-Dist: pytest-cov<8.0.0,>=4.1.0; extra == 'testing'
Requires-Dist: pytest<10.0.0,>=7.1.3; extra == 'testing'
Requires-Dist: pytz; extra == 'testing'
Requires-Dist: redis; extra == 'testing'
Requires-Dist: structlog>=25.2.0; extra == 'testing'
Requires-Dist: types-orjson==3.6.2; extra == 'testing'
Requires-Dist: types-ujson==5.10.0.20250822; extra == 'testing'
Requires-Dist: ujson<6,>=5.7.0; extra == 'testing'
